{
 "channels": [
  {
   "id": "aura",
   "name": "Aura",
   "programs_with_chat": 3,
   "chat_messages": 6039,
   "msgs_per_1k": 48.15,
   "noise_score": 0.94,
   "chat_quality_tier": "media",
   "chat_quality_label": "Comunidad moderada",
   "paid_events": 0,
   "mix": {
    "emoji_pct": 0.1,
    "saludo_pct": 0.0,
    "reaccion_pct": 1.1,
    "pregunta_pct": 95.8,
    "demanda_pct": 0.1,
    "obediencia_pct": 0.1,
    "apoyo_pct": 0.0,
    "texto_pct": 2.8
   },
   "character_label": "Comunidad activa — chat denso respecto a la audiencia",
   "top_demands": [
    {
     "text": "A Tinder le sirve que no duren las parejas para que vuelvan a la APP.",
     "tipo": "pedido_link",
     "count": 1
    },
    {
     "text": "MANDEN SUS AUDIOS: 11 7080 4460 :sparkles:",
     "tipo": "pregunta_compra",
     "count": 1
    },
    {
     "text": "779 es el codigo de argentina despues 750 → México.789–790 → Brasil.690–699 → Ch",
     "tipo": "pedido_link",
     "count": 1
    },
    {
     "text": "¿QUÉ TE HUBIERA GUSTADO INVENTAR? Manden sus audios: 11 7080 4460 :sparkles:",
     "tipo": "pregunta_compra",
     "count": 1
    },
    {
     "text": "Manden sus inventos en un audio: 11 7080 4460 :sparkles:",
     "tipo": "pregunta_compra",
     "count": 1
    }
   ]
  },
  {
   "id": "ahoraplay",
   "name": "Ahora Play",
   "programs_with_chat": 4,
   "chat_messages": 4882,
   "msgs_per_1k": 23.3,
   "noise_score": 0.46,
   "chat_quality_tier": "alta",
   "chat_quality_label": "Comunidad activa",
   "paid_events": 0,
   "mix": {
    "emoji_pct": 0.1,
    "saludo_pct": 0.1,
    "reaccion_pct": 1.6,
    "pregunta_pct": 89.0,
    "demanda_pct": 0.4,
    "obediencia_pct": 0.4,
    "apoyo_pct": 0.0,
    "texto_pct": 8.4
   },
   "character_label": "Comunidad activa — chat denso respecto a la audiencia",
   "top_demands": [
    {
     "text": "las fintech te ofrecían prestamos por aplicación, sin análisis de riesgo, y para",
     "tipo": "otro",
     "count": 1
    },
    {
     "text": "el dolarquedo com el mismo precio y todo subió.donde estamos?",
     "tipo": "pregunta_precio",
     "count": 1
    },
    {
     "text": "Fernando, con lo que están encanutando en los silos los productores, qué crees v",
     "tipo": "otro",
     "count": 1
    },
    {
     "text": "Martín, cuando sale un \"ASAD bursatil\" en zona sur?",
     "tipo": "pregunta_precio",
     "count": 1
    },
    {
     "text": "CICLO DE LAS MEMORIAS 3 AÑOS ALCISTA Y DESPUÉS CAEN AUMENTA EL PRECIO CAE LA DEM",
     "tipo": "pregunta_precio",
     "count": 1
    }
   ]
  },
  {
   "id": "neura",
   "name": "Neura Media",
   "programs_with_chat": 10,
   "chat_messages": 4194,
   "msgs_per_1k": 16.06,
   "noise_score": 0.05,
   "chat_quality_tier": "alta",
   "chat_quality_label": "Comunidad activa",
   "paid_events": 38,
   "mix": {
    "emoji_pct": 1.4,
    "saludo_pct": 1.5,
    "reaccion_pct": 30.0,
    "pregunta_pct": 24.5,
    "demanda_pct": 1.0,
    "obediencia_pct": 1.3,
    "apoyo_pct": 0.9,
    "texto_pct": 39.6
   },
   "character_label": "Comunidad activa — chat denso respecto a la audiencia",
   "top_demands": [
    {
     "text": "Flaco no sé si esta programado, pero hablen de Mbappe bajando línea a toda la se",
     "tipo": "pedido_contenido",
     "count": 3
    },
    {
     "text": "Y DE DONDE SALE ESA REGLAMENTACION EN EL SENADO...?????",
     "tipo": "pregunta_precio",
     "count": 1
    },
    {
     "text": "A DIETA ??? @jultarres ??? pesabas 48 Kg dijiste ??? a cuánto vas a bajar ??? UH",
     "tipo": "pregunta_precio",
     "count": 1
    },
    {
     "text": "@PatanPerroloco Deja la payasada. Lo dijo el compañero de Joni Viale que siempre",
     "tipo": "otro",
     "count": 1
    },
    {
     "text": "PATAN NO QUIERO PROBAR SI EM SALE MAL",
     "tipo": "pregunta_precio",
     "count": 1
    }
   ]
  },
  {
   "id": "",
   "name": "",
   "programs_with_chat": 16,
   "chat_messages": 28117,
   "msgs_per_1k": 9.17,
   "noise_score": 0.21,
   "chat_quality_tier": "alta",
   "chat_quality_label": "Comunidad activa",
   "paid_events": 40,
   "mix": {
    "emoji_pct": 2.7,
    "saludo_pct": 1.0,
    "reaccion_pct": 35.5,
    "pregunta_pct": 24.9,
    "demanda_pct": 0.9,
    "obediencia_pct": 0.8,
    "apoyo_pct": 0.1,
    "texto_pct": 34.0
   },
   "character_label": "Comunidad activa — chat denso respecto a la audiencia",
   "top_demands": [
    {
     "text": "YO APOYO A MILEI, PERO QUE NO SE MANDEN CAGADAS !!! Y AFANEN, SI VENIAN A HACER ",
     "tipo": "pregunta_compra",
     "count": 10
    },
    {
     "text": "hablen de las bombas de E.E.U.U. que son para hacer terremoto o bombas para hace",
     "tipo": "pedido_contenido",
     "count": 6
    },
    {
     "text": "Tomas rebord no me cae bien, pero deablos, necesito que venga a Gelatina",
     "tipo": "pedido_contenido",
     "count": 4
    },
    {
     "text": "HABLEN DE TESORIN QUE SE CHOREARON UN GASODUCTO EN SALTA PARA TRAER A RICKY MART",
     "tipo": "pedido_contenido",
     "count": 4
    },
    {
     "text": "¿¿¿HABLEN DE LAS SOCIEDADES OFFSHORE DE SANTILLI O LOS SOBRES $$$ NO SE LO PERMI",
     "tipo": "pedido_contenido",
     "count": 3
    }
   ]
  },
  {
   "id": "vorterix",
   "name": "Vorterix",
   "programs_with_chat": 16,
   "chat_messages": 57560,
   "msgs_per_1k": 4.85,
   "noise_score": 0.08,
   "chat_quality_tier": "alta",
   "chat_quality_label": "Comunidad activa",
   "paid_events": 75,
   "mix": {
    "emoji_pct": 1.8,
    "saludo_pct": 0.7,
    "reaccion_pct": 45.2,
    "pregunta_pct": 17.3,
    "demanda_pct": 0.7,
    "obediencia_pct": 1.0,
    "apoyo_pct": 0.1,
    "texto_pct": 33.3
   },
   "character_label": "Comunidad activa — chat denso respecto a la audiencia",
   "top_demands": [
    {
     "text": "LLAMEN A FIO",
     "tipo": "pedido_contenido",
     "count": 14
    },
    {
     "text": "HABLEN DE LA MEADA DEL CHIQUI A EDUL",
     "tipo": "pedido_contenido",
     "count": 9
    },
    {
     "text": "Muchachooos! Hablen del conflicto en Blender!! Llamen a Fio Sargenti!!!",
     "tipo": "pedido_contenido",
     "count": 6
    },
    {
     "text": "PASA EL LINK GUICHE",
     "tipo": "pedido_link",
     "count": 4
    },
    {
     "text": "hablen de adorni",
     "tipo": "pedido_contenido",
     "count": 2
    }
   ]
  },
  {
   "id": "cronista",
   "name": "El Cronista",
   "programs_with_chat": 3,
   "chat_messages": 844,
   "msgs_per_1k": 2.77,
   "noise_score": 0.21,
   "chat_quality_tier": "media",
   "chat_quality_label": "Comunidad moderada",
   "paid_events": 2,
   "mix": {
    "emoji_pct": 0.0,
    "saludo_pct": 0.5,
    "reaccion_pct": 10.7,
    "pregunta_pct": 66.8,
    "demanda_pct": 0.5,
    "obediencia_pct": 0.1,
    "apoyo_pct": 0.2,
    "texto_pct": 21.2
   },
   "character_label": "Comunidad activa — chat denso respecto a la audiencia",
   "top_demands": [
    {
     "text": "Que hablen de Kiciloff como candidato me parece comico pero bueno puede ser que ",
     "tipo": "pedido_contenido",
     "count": 1
    },
    {
     "text": "cuál es el link??",
     "tipo": "pedido_link",
     "count": 1
    },
    {
     "text": "cual es el fundamento que respalda el precio del Bitcoin ??",
     "tipo": "pregunta_precio",
     "count": 1
    },
    {
     "text": "10 % de descuento en revoque grueso , hoy vamos paraguay",
     "tipo": "pedido_link",
     "count": 1
    }
   ]
  },
  {
   "id": "gelatina",
   "name": "Gelatina",
   "programs_with_chat": 7,
   "chat_messages": 5609,
   "msgs_per_1k": 2.69,
   "noise_score": 0.15,
   "chat_quality_tier": "alta",
   "chat_quality_label": "Comunidad activa",
   "paid_events": 4,
   "mix": {
    "emoji_pct": 2.4,
    "saludo_pct": 2.6,
    "reaccion_pct": 32.1,
    "pregunta_pct": 24.9,
    "demanda_pct": 0.9,
    "obediencia_pct": 0.7,
    "apoyo_pct": 0.1,
    "texto_pct": 36.4
   },
   "character_label": "Comunidad activa — chat denso respecto a la audiencia",
   "top_demands": [
    {
     "text": "vamos pepe decime cuanto aumento cuota para incorporar HAA",
     "tipo": "pregunta_precio",
     "count": 1
    },
    {
     "text": "en cualquier momento sale a jugar Bisman",
     "tipo": "pregunta_precio",
     "count": 1
    },
    {
     "text": "Este tipo me genera una violencia que me cuesta describir",
     "tipo": "pregunta_precio",
     "count": 1
    },
    {
     "text": "sturze sale segundo hace 2 meses",
     "tipo": "pregunta_precio",
     "count": 1
    },
    {
     "text": "rebor es el primer perjudicado. Hablen de gusto chat. Tomas ya va hablar",
     "tipo": "pedido_contenido",
     "count": 1
    }
   ]
  },
  {
   "id": "blend",
   "name": "Blender",
   "programs_with_chat": 4,
   "chat_messages": 8656,
   "msgs_per_1k": 2.59,
   "noise_score": 0.12,
   "chat_quality_tier": "alta",
   "chat_quality_label": "Comunidad activa",
   "paid_events": 0,
   "mix": {
    "emoji_pct": 3.8,
    "saludo_pct": 0.5,
    "reaccion_pct": 45.9,
    "pregunta_pct": 16.1,
    "demanda_pct": 0.7,
    "obediencia_pct": 0.2,
    "apoyo_pct": 0.0,
    "texto_pct": 32.9
   },
   "character_label": "Comunidad activa — chat denso respecto a la audiencia",
   "top_demands": [
    {
     "text": "fah yo trabajé como moderadora de contenido para una app!",
     "tipo": "pedido_link",
     "count": 2
    },
    {
     "text": "sale only",
     "tipo": "pregunta_precio",
     "count": 1
    },
    {
     "text": "¿Donde está Moreno? ¿Cuanto falta para que llegue?",
     "tipo": "pregunta_precio",
     "count": 1
    },
    {
     "text": "LE CUESTA A LU .. PERO ESTE GUILLE ES!!!",
     "tipo": "pregunta_precio",
     "count": 1
    },
    {
     "text": "el conmgelador de precio",
     "tipo": "pregunta_precio",
     "count": 1
    }
   ]
  },
  {
   "id": "cenital",
   "name": "Cenital",
   "programs_with_chat": 2,
   "chat_messages": 518,
   "msgs_per_1k": 1.09,
   "noise_score": 0.01,
   "chat_quality_tier": "media",
   "chat_quality_label": "Comunidad moderada",
   "paid_events": 0,
   "mix": {
    "emoji_pct": 0.4,
    "saludo_pct": 0.4,
    "reaccion_pct": 25.5,
    "pregunta_pct": 31.5,
    "demanda_pct": 0.9,
    "obediencia_pct": 1.2,
    "apoyo_pct": 0.0,
    "texto_pct": 40.2
   },
   "character_label": "Comunidad moderada",
   "top_demands": [
    {
     "text": "Un monitor gamer, averiguen con cuanto se queda Karina. SAdorni ya fue.",
     "tipo": "pregunta_precio",
     "count": 1
    },
    {
     "text": "Hasta que vaya preso",
     "tipo": "pedido_contenido",
     "count": 1
    },
    {
     "text": "lo que no sabemos es todo lo que aún no gasto. cuánto tiene?",
     "tipo": "pregunta_precio",
     "count": 1
    },
    {
     "text": "Además este mundial es un afanó. Tienen idea el precio de las entradas?",
     "tipo": "pregunta_precio",
     "count": 1
    },
    {
     "text": "@santgr vot sí",
     "tipo": "voto_eleccion",
     "count": 1
    }
   ]
  },
  {
   "id": "olga",
   "name": "Olga",
   "programs_with_chat": 24,
   "chat_messages": 87415,
   "msgs_per_1k": 0.98,
   "noise_score": 0.17,
   "chat_quality_tier": "alta",
   "chat_quality_label": "Comunidad activa",
   "paid_events": 4,
   "mix": {
    "emoji_pct": 11.5,
    "saludo_pct": 0.4,
    "reaccion_pct": 39.3,
    "pregunta_pct": 14.5,
    "demanda_pct": 0.7,
    "obediencia_pct": 1.0,
    "apoyo_pct": 0.0,
    "texto_pct": 32.7
   },
   "character_label": "Comunidad moderada",
   "top_demands": [
    {
     "text": ":bird::bird::bird::bird::bird::bird::bird::bird:LOCO TRAIGAN A CHAROOOOOOOOOOOOO",
     "tipo": "pedido_contenido",
     "count": 61
    },
    {
     "text": "LLAMEN A RECHI",
     "tipo": "pedido_contenido",
     "count": 25
    },
    {
     "text": "LOCO TRAIGAN A CHAROOOOOOOOOOOOOOOOOOOOOOOOOOO",
     "tipo": "pedido_contenido",
     "count": 14
    },
    {
     "text": "CHICOS Q BIEN LE SALE DIOS",
     "tipo": "pregunta_precio",
     "count": 6
    },
    {
     "text": "Cuál es la app de cómo saber la música??",
     "tipo": "pedido_link",
     "count": 4
    }
   ]
  },
  {
   "id": "urbana_play_104.3_fm",
   "name": "urbana_play_104.3_fm",
   "programs_with_chat": 3,
   "chat_messages": 10367,
   "msgs_per_1k": 0.61,
   "noise_score": 0.22,
   "chat_quality_tier": "media",
   "chat_quality_label": "Comunidad moderada",
   "paid_events": 0,
   "mix": {
    "emoji_pct": 1.8,
    "saludo_pct": 1.4,
    "reaccion_pct": 26.2,
    "pregunta_pct": 24.0,
    "demanda_pct": 0.7,
    "obediencia_pct": 0.3,
    "apoyo_pct": 0.0,
    "texto_pct": 45.7
   },
   "character_label": "Comunidad moderada",
   "top_demands": [
    {
     "text": "sale el ladrón de Adorno y entra el colorado, otro ladrón con cuántas propiedade",
     "tipo": "pregunta_precio",
     "count": 1
    },
    {
     "text": "3:50 Am Saludos hermanos Argentinos , son unos chingones, saludos desde aquí ciu",
     "tipo": "otro",
     "count": 1
    },
    {
     "text": "sale duchaja?",
     "tipo": "pregunta_precio",
     "count": 1
    },
    {
     "text": "ahora sale tweet del Presidente sobre el tema del saquito",
     "tipo": "pregunta_precio",
     "count": 1
    },
    {
     "text": "sale el editorial de la mechera",
     "tipo": "pregunta_precio",
     "count": 1
    }
   ]
  },
  {
   "id": "bondi",
   "name": "Bondi Live",
   "programs_with_chat": 2,
   "chat_messages": 9004,
   "msgs_per_1k": 0.52,
   "noise_score": 0.23,
   "chat_quality_tier": "media",
   "chat_quality_label": "Comunidad moderada",
   "paid_events": 2,
   "mix": {
    "emoji_pct": 2.2,
    "saludo_pct": 0.6,
    "reaccion_pct": 34.2,
    "pregunta_pct": 22.4,
    "demanda_pct": 0.4,
    "obediencia_pct": 1.8,
    "apoyo_pct": 0.0,
    "texto_pct": 38.3
   },
   "character_label": "Comunidad moderada",
   "top_demands": [
    {
     "text": "LINK LINK LINK",
     "tipo": "pedido_link",
     "count": 2
    },
    {
     "text": "llamen a Castelo.",
     "tipo": "pedido_contenido",
     "count": 1
    },
    {
     "text": "Bueno. Si alguna sale con Santi que no se queje, eh!",
     "tipo": "pregunta_precio",
     "count": 1
    },
    {
     "text": "pero podes darla de baja al toque con la app",
     "tipo": "pedido_link",
     "count": 1
    },
    {
     "text": "cuanto salen esos mic mini?",
     "tipo": "pregunta_precio",
     "count": 1
    }
   ]
  },
  {
   "id": "azz",
   "name": "AZZ",
   "programs_with_chat": 1,
   "chat_messages": 97,
   "msgs_per_1k": 0.31,
   "noise_score": 0.01,
   "chat_quality_tier": "baja",
   "chat_quality_label": "Poca actividad en chat",
   "paid_events": 0,
   "mix": {
    "emoji_pct": 4.1,
    "saludo_pct": 0.0,
    "reaccion_pct": 34.0,
    "pregunta_pct": 21.6,
    "demanda_pct": 1.0,
    "obediencia_pct": 1.0,
    "apoyo_pct": 0.0,
    "texto_pct": 38.1
   },
   "character_label": "Comunidad moderada",
   "top_demands": [
    {
     "text": "saludos desde Juan Lacaze, manden saludos :saluting_face:",
     "tipo": "pregunta_compra",
     "count": 1
    }
   ]
  },
  {
   "id": "border",
   "name": "BorderPeriodismo",
   "programs_with_chat": 1,
   "chat_messages": 25,
   "msgs_per_1k": 0.09,
   "noise_score": 0.0,
   "chat_quality_tier": "baja",
   "chat_quality_label": "Poca actividad en chat",
   "paid_events": 0,
   "mix": {
    "emoji_pct": 0.0,
    "saludo_pct": 0.0,
    "reaccion_pct": 12.0,
    "pregunta_pct": 28.0,
    "demanda_pct": 4.0,
    "obediencia_pct": 0.0,
    "apoyo_pct": 0.0,
    "texto_pct": 56.0
   },
   "character_label": "Comunidad moderada",
   "top_demands": [
    {
     "text": "El proyecto del Banco Mundial es el Préstamo BIRF N.º 9748-AR (con código intern",
     "tipo": "pedido_link",
     "count": 1
    }
   ]
  }
 ],
 "top_programs": [
  {
   "video_id": "c1LrQSDaXAY",
   "title": "Neura De Gira ✈️ | Con Naty y Denu Palmeiro",
   "channel": "Neura Media",
   "chat_messages": 463,
   "chat_events": 463,
   "paid_events": 2,
   "msgs_per_1k": 72.12,
   "noise_score": 0.12,
   "mix": {
    "emoji_pct": 4.8,
    "saludo_pct": 3.2,
    "reaccion_pct": 49.7,
    "pregunta_pct": 13.0,
    "demanda_pct": 1.1,
    "obediencia_pct": 0.6,
    "apoyo_pct": 0.4,
    "texto_pct": 27.2
   },
   "character_label": "Comunidad conversadora — chat activo más allá de emojis",
   "top_words": [
    {
     "word": "gracias",
     "count": 17
    },
    {
     "word": "sebastian",
     "count": 14
    },
    {
     "word": "crucero",
     "count": 12
    },
    {
     "word": "tengo",
     "count": 11
    },
    {
     "word": "gano",
     "count": 9
    },
    {
     "word": "espana",
     "count": 9
    }
   ],
   "top_demands": [
    {
     "text": "(no menejo en la ciudad igualmente)",
     "tipo": "voto_eleccion",
     "count": 1
    },
    {
     "text": "SALE DEL TIGRE",
     "tipo": "pregunta_precio",
     "count": 1
    },
    {
     "text": "quiero ir a vivir a ese crucero. Cuánto el alquiler mensual y expensas?",
     "tipo": "pregunta_precio",
     "count": 1
    },
    {
     "text": "SALE DEL TIGRE?",
     "tipo": "pregunta_precio",
     "count": 1
    },
    {
     "text": "Muy buen momento cuanto estamos aprendiendo!!",
     "tipo": "pregunta_precio",
     "count": 1
    }
   ],
   "channel_id": "neura"
  },
  {
   "video_id": "NZnTfvrPb0E",
   "title": "🟠 ¿CÓMO QUEDARON LOS CRUCES DEL  MUNDIAL 2026? l HOY COMO SIEMPRE",
   "channel": " A U R A ",
   "chat_messages": 2002,
   "chat_events": 2002,
   "paid_events": 0,
   "msgs_per_1k": 57.02,
   "noise_score": 0.95,
   "mix": {
    "emoji_pct": 0.1,
    "saludo_pct": 0.0,
    "reaccion_pct": 0.5,
    "pregunta_pct": 96.9,
    "demanda_pct": 0.1,
    "obediencia_pct": 0.1,
    "apoyo_pct": 0.0,
    "texto_pct": 2.3
   },
   "character_label": "Comunidad conversadora — chat activo más allá de emojis",
   "top_words": [
    {
     "word": "cual",
     "count": 1910
    },
    {
     "word": "mejor",
     "count": 1908
    },
    {
     "word": "viral",
     "count": 1908
    },
    {
     "word": "mundialista",
     "count": 1908
    },
    {
     "word": "buen",
     "count": 9
    },
    {
     "word": "hernan",
     "count": 8
    }
   ],
   "top_demands": [
    {
     "text": "¿QUÉ TE HUBIERA GUSTADO INVENTAR? Manden sus audios: 11 7080 4460 :sparkles:",
     "tipo": "pregunta_compra",
     "count": 1
    },
    {
     "text": "Manden sus inventos en un audio: 11 7080 4460 :sparkles:",
     "tipo": "pregunta_compra",
     "count": 1
    }
   ],
   "channel_id": "aura"
  },
  {
   "video_id": "LjIm9sAasxA",
   "title": "",
   "channel": "",
   "chat_messages": 50,
   "chat_events": 50,
   "paid_events": 0,
   "msgs_per_1k": 52.08,
   "noise_score": 0.96,
   "mix": {
    "emoji_pct": 0.0,
    "saludo_pct": 0.0,
    "reaccion_pct": 0.0,
    "pregunta_pct": 98.0,
    "demanda_pct": 0.0,
    "obediencia_pct": 0.0,
    "apoyo_pct": 0.0,
    "texto_pct": 2.0
   },
   "character_label": "Comunidad conversadora — chat activo más allá de emojis",
   "top_words": [
    {
     "word": "adorni",
     "count": 49
    },
    {
     "word": "renuncia",
     "count": 49
    },
    {
     "word": "impacta",
     "count": 49
    },
    {
     "word": "milei",
     "count": 49
    }
   ],
   "top_demands": [],
   "channel_id": ""
  },
  {
   "video_id": "gOUmUVtulaw",
   "title": "LA NUEVA ETAPA DEL DÓLAR Y MORA RÉCORD I Carlos Burgueño, Agustina Girón #CierreDeMercados",
   "channel": "AHORA PLAY",
   "chat_messages": 1275,
   "chat_events": 1275,
   "paid_events": 0,
   "msgs_per_1k": 49.16,
   "noise_score": 0.96,
   "mix": {
    "emoji_pct": 0.0,
    "saludo_pct": 0.0,
    "reaccion_pct": 0.3,
    "pregunta_pct": 97.5,
    "demanda_pct": 0.1,
    "obediencia_pct": 0.0,
    "apoyo_pct": 0.0,
    "texto_pct": 2.1
   },
   "character_label": "Comunidad conversadora — chat activo más allá de emojis",
   "top_words": [
    {
     "word": "tarjeta",
     "count": 1222
    },
    {
     "word": "haces",
     "count": 1218
    },
    {
     "word": "gastos",
     "count": 1218
    },
    {
     "word": "dolares",
     "count": 5
    },
    {
     "word": "michel",
     "count": 5
    },
    {
     "word": "educacion",
     "count": 4
    }
   ],
   "top_demands": [
    {
     "text": "las fintech te ofrecían prestamos por aplicación, sin análisis de riesgo, y para encontrar la tasa d",
     "tipo": "otro",
     "count": 1
    }
   ],
   "channel_id": "ahoraplay"
  },
  {
   "video_id": "AUSgxGQirlM",
   "title": "LA CIENCIA DE LOS CODIGOS QR con EZE MARTÍNEZ l #deacá - 29/06/26",
   "channel": " A U R A ",
   "chat_messages": 2193,
   "chat_events": 2193,
   "paid_events": 0,
   "msgs_per_1k": 48.52,
   "noise_score": 0.95,
   "mix": {
    "emoji_pct": 0.0,
    "saludo_pct": 0.0,
    "reaccion_pct": 1.5,
    "pregunta_pct": 95.9,
    "demanda_pct": 0.1,
    "obediencia_pct": 0.0,
    "apoyo_pct": 0.0,
    "texto_pct": 2.5
   },
   "character_label": "Comunidad conversadora — chat activo más allá de emojis",
   "top_words": [
    {
     "word": "responder",
     "count": 1851
    },
    {
     "word": "olvidas",
     "count": 1850
    },
    {
     "word": "mensajes",
     "count": 1850
    },
    {
     "word": "ustedes",
     "count": 141
    },
    {
     "word": "bien",
     "count": 140
    },
    {
     "word": "matematicas",
     "count": 139
    }
   ],
   "top_demands": [
    {
     "text": "MANDEN SUS AUDIOS: 11 7080 4460 :sparkles:",
     "tipo": "pregunta_compra",
     "count": 1
    },
    {
     "text": "779 es el codigo de argentina despues 750 → México.789–790 → Brasil.690–699 → China.500–509 → Reino ",
     "tipo": "pedido_link",
     "count": 1
    }
   ],
   "channel_id": "aura"
  },
  {
   "video_id": "HTm_q34CwyM",
   "title": "MILEI REINICIA SU GOBIERNO I Claudio Zlotnik Paula Macchi Matías Battista #SerruchoEconómico",
   "channel": "AHORA PLAY",
   "chat_messages": 3480,
   "chat_events": 3480,
   "paid_events": 0,
   "msgs_per_1k": 40.42,
   "noise_score": 0.79,
   "mix": {
    "emoji_pct": 0.1,
    "saludo_pct": 0.1,
    "reaccion_pct": 1.6,
    "pregunta_pct": 87.9,
    "demanda_pct": 0.4,
    "obediencia_pct": 0.5,
    "apoyo_pct": 0.0,
    "texto_pct": 9.4
   },
   "character_label": "Comunidad conversadora — chat activo más allá de emojis",
   "top_words": [
    {
     "word": "milei",
     "count": 2809
    },
    {
     "word": "adorni",
     "count": 2801
    },
    {
     "word": "renuncia",
     "count": 2743
    },
    {
     "word": "crees",
     "count": 2741
    },
    {
     "word": "repercute",
     "count": 2740
    },
    {
     "word": "face",
     "count": 78
    }
   ],
   "top_demands": [
    {
     "text": "Milei ofrece milanesas otra ves con el precio de la carne otro gasto:face-blue-smiling:",
     "tipo": "pregunta_precio",
     "count": 1
    },
    {
     "text": "Si rajan a Adorni y otros políticos de YPF, seguro pueden bajar precio las naftas...",
     "tipo": "pregunta_precio",
     "count": 1
    },
    {
     "text": "Un saludo desde la ciudad de Santa Fe. Buena Semana, Gente...",
     "tipo": "voto_eleccion",
     "count": 1
    },
    {
     "text": "gobierno de anglojudea inoperante y terminado, que venga el enano soviético nomás",
     "tipo": "pedido_contenido",
     "count": 1
    },
    {
     "text": "PREGUNTO ADORNI SALE DE LOS NEGOCIOS CON EL ESTADO... POR EJEMPLO CON YPF",
     "tipo": "pregunta_precio",
     "count": 1
    }
   ],
   "channel_id": "ahoraplay"
  },
  {
   "video_id": "FQ2cHqcRZbQ",
   "title": "🔵 CHARLA SIN FILTRO con GRACIELA ALFANO en DE ACÁ 2026-06-30 10:10",
   "channel": " A U R A ",
   "chat_messages": 1844,
   "chat_events": 1844,
   "paid_events": 0,
   "msgs_per_1k": 38.92,
   "noise_score": 0.92,
   "mix": {
    "emoji_pct": 0.2,
    "saludo_pct": 0.0,
    "reaccion_pct": 1.2,
    "pregunta_pct": 94.6,
    "demanda_pct": 0.1,
    "obediencia_pct": 0.2,
    "apoyo_pct": 0.0,
    "texto_pct": 3.7
   },
   "character_label": "Comunidad conversadora — chat activo más allá de emojis",
   "top_words": [
    {
     "word": "buenos",
     "count": 851
    },
    {
     "word": "parejas",
     "count": 848
    },
    {
     "word": "armando",
     "count": 847
    },
    {
     "word": "abogado",
     "count": 842
    },
    {
     "word": "nacho",
     "count": 426
    },
    {
     "word": "malo",
     "count": 425
    }
   ],
   "top_demands": [
    {
     "text": "A Tinder le sirve que no duren las parejas para que vuelvan a la APP.",
     "tipo": "pedido_link",
     "count": 1
    }
   ],
   "channel_id": "aura"
  },
  {
   "video_id": "-FYveSXX_NA",
   "title": "",
   "channel": "",
   "chat_messages": 1098,
   "chat_events": 1098,
   "paid_events": 0,
   "msgs_per_1k": 32.74,
   "noise_score": 0.87,
   "mix": {
    "emoji_pct": 0.1,
    "saludo_pct": 0.1,
    "reaccion_pct": 3.2,
    "pregunta_pct": 89.8,
    "demanda_pct": 0.2,
    "obediencia_pct": 0.0,
    "apoyo_pct": 0.0,
    "texto_pct": 6.6
   },
   "character_label": "Comunidad conversadora — chat activo más allá de emojis",
   "top_words": [
    {
     "word": "finanzas",
     "count": 494
    },
    {
     "word": "llevas",
     "count": 493
    },
    {
     "word": "personaje",
     "count": 233
    },
    {
     "word": "quien",
     "count": 231
    },
    {
     "word": "menos",
     "count": 231
    },
    {
     "word": "adivina",
     "count": 230
    }
   ],
   "top_demands": [
    {
     "text": "Mendoza, la ciudad que financió el cruce de los Andes del Gran General!",
     "tipo": "voto_eleccion",
     "count": 1
    },
    {
     "text": "¿Se animan a sumarse al juego? Manden al chat sus pistas :sparkles:",
     "tipo": "pregunta_compra",
     "count": 1
    }
   ],
   "channel_id": ""
  },
  {
   "video_id": "VRWovoLU0yQ",
   "title": "🍿 Plot Twist 👾",
   "channel": "Neura Media",
   "chat_messages": 417,
   "chat_events": 417,
   "paid_events": 0,
   "msgs_per_1k": 21.84,
   "noise_score": 0.02,
   "mix": {
    "emoji_pct": 2.2,
    "saludo_pct": 0.5,
    "reaccion_pct": 29.7,
    "pregunta_pct": 29.3,
    "demanda_pct": 1.2,
    "obediencia_pct": 0.2,
    "apoyo_pct": 0.0,
    "texto_pct": 36.9
   },
   "character_label": "Comunidad conversadora — chat activo más allá de emojis",
   "top_words": [
    {
     "word": "face",
     "count": 25
    },
    {
     "word": "smiling",
     "count": 25
    },
    {
     "word": "blue",
     "count": 22
    },
    {
     "word": "mejor",
     "count": 17
    },
    {
     "word": "pelicula",
     "count": 17
    },
    {
     "word": "superman",
     "count": 16
    }
   ],
   "top_demands": [
    {
     "text": "que venga grabois a hablar de tolkien jaj",
     "tipo": "pedido_contenido",
     "count": 1
    },
    {
     "text": "cuando atacan la ciudad de los africanos... puro bodrio",
     "tipo": "voto_eleccion",
     "count": 1
    },
    {
     "text": "la moda es que sale la web novel, de ahi la light novel, de ahi el anime",
     "tipo": "pregunta_precio",
     "count": 1
    },
    {
     "text": "mi viejo es fanatico de marvel especificamente del capitan america, al principio yo era team marvel ",
     "tipo": "otro",
     "count": 1
    },
    {
     "text": "hablando de Henry Cavill, cuando carajos sale el trailer de Highlander 2026... !!!!!!!!!!!!",
     "tipo": "pregunta_precio",
     "count": 1
    }
   ],
   "channel_id": "neura"
  },
  {
   "video_id": "DMOHJbfdIlY",
   "title": "",
   "channel": "",
   "chat_messages": 1076,
   "chat_events": 1076,
   "paid_events": 22,
   "msgs_per_1k": 14.44,
   "noise_score": 0.22,
   "mix": {
    "emoji_pct": 0.2,
    "saludo_pct": 0.7,
    "reaccion_pct": 17.5,
    "pregunta_pct": 33.1,
    "demanda_pct": 2.3,
    "obediencia_pct": 0.9,
    "apoyo_pct": 2.0,
    "texto_pct": 43.2
   },
   "character_label": "Comunidad conversadora — chat activo más allá de emojis",
   "top_words": [
    {
     "word": "adorni",
     "count": 131
    },
    {
     "word": "otto",
     "count": 122
    },
    {
     "word": "facewithtearsofjoy",
     "count": 58
    },
    {
     "word": "macri",
     "count": 50
    },
    {
     "word": "viejo",
     "count": 47
    },
    {
     "word": "agustin",
     "count": 46
    }
   ],
   "top_demands": [
    {
     "text": "YO APOYO A MILEI, PERO QUE NO SE MANDEN CAGADAS !!! Y AFANEN, SI VENIAN A HACER LO CONTRARIO A LOS K",
     "tipo": "pregunta_compra",
     "count": 10
    },
    {
     "text": "HABLEN DE TESORIN QUE SE CHOREARON UN GASODUCTO EN SALTA PARA TRAER A RICKY MARTIN",
     "tipo": "pedido_contenido",
     "count": 4
    },
    {
     "text": "¿¿¿HABLEN DE LAS SOCIEDADES OFFSHORE DE SANTILLI O LOS SOBRES $$$ NO SE LO PERMITEN'???",
     "tipo": "pedido_contenido",
     "count": 3
    },
    {
     "text": "Macri se sacó un competidor de la ciudad",
     "tipo": "voto_eleccion",
     "count": 1
    },
    {
     "text": "Uhh cuanto enojo! Que adentro que la tienen por favor",
     "tipo": "pregunta_precio",
     "count": 1
    }
   ],
   "channel_id": ""
  }
 ],
 "demand_signals": [
  {
   "text": ":bird::bird::bird::bird::bird::bird::bird::bird:LOCO TRAIGAN A CHAROOOOOOOOOOOOOOOOOOOOOOOOOOO:bird:",
   "tipo": "pedido_contenido",
   "count": 61,
   "n_programas": 1,
   "canales": [
    "OLGA"
   ],
   "cross_canal": false
  },
  {
   "text": "LLAMEN A RECHI",
   "tipo": "pedido_contenido",
   "count": 25,
   "n_programas": 1,
   "canales": [
    "OLGA"
   ],
   "cross_canal": false
  },
  {
   "text": "LOCO TRAIGAN A CHAROOOOOOOOOOOOOOOOOOOOOOOOOOO",
   "tipo": "pedido_contenido",
   "count": 14,
   "n_programas": 1,
   "canales": [
    "OLGA"
   ],
   "cross_canal": false
  },
  {
   "text": "LLAMEN A FIO",
   "tipo": "pedido_contenido",
   "count": 14,
   "n_programas": 1,
   "canales": [
    "Vorterix"
   ],
   "cross_canal": false
  },
  {
   "text": "YO APOYO A MILEI, PERO QUE NO SE MANDEN CAGADAS !!! Y AFANEN, SI VENIAN A HACER LO CONTRARIO A LOS K",
   "tipo": "pregunta_compra",
   "count": 10,
   "n_programas": 1,
   "canales": [],
   "cross_canal": false
  },
  {
   "text": "HABLEN DE LA MEADA DEL CHIQUI A EDUL",
   "tipo": "pedido_contenido",
   "count": 9,
   "n_programas": 1,
   "canales": [
    "Vorterix"
   ],
   "cross_canal": false
  },
  {
   "text": "CHICOS Q BIEN LE SALE DIOS",
   "tipo": "pregunta_precio",
   "count": 6,
   "n_programas": 1,
   "canales": [
    "OLGA"
   ],
   "cross_canal": false
  },
  {
   "text": "Muchachooos! Hablen del conflicto en Blender!! Llamen a Fio Sargenti!!!",
   "tipo": "pedido_contenido",
   "count": 6,
   "n_programas": 1,
   "canales": [
    "Vorterix"
   ],
   "cross_canal": false
  },
  {
   "text": "hablen de las bombas de E.E.U.U. que son para hacer terremoto o bombas para hacer tsunami o maquinas",
   "tipo": "pedido_contenido",
   "count": 6,
   "n_programas": 1,
   "canales": [],
   "cross_canal": false
  },
  {
   "text": "Tomas rebord no me cae bien, pero deablos, necesito que venga a Gelatina",
   "tipo": "pedido_contenido",
   "count": 4,
   "n_programas": 1,
   "canales": [],
   "cross_canal": false
  },
  {
   "text": "PASA EL LINK GUICHE",
   "tipo": "pedido_link",
   "count": 4,
   "n_programas": 1,
   "canales": [
    "Vorterix"
   ],
   "cross_canal": false
  },
  {
   "text": "HABLEN DE TESORIN QUE SE CHOREARON UN GASODUCTO EN SALTA PARA TRAER A RICKY MARTIN",
   "tipo": "pedido_contenido",
   "count": 4,
   "n_programas": 1,
   "canales": [],
   "cross_canal": false
  }
 ],
 "platform_line": "Aura es donde más habla la sala (48.15 mensajes por cada mil mirando). Demanda recurrente: «:bird::bird::bird::bird::bird::bird::bird::bird:LOCO TRAIGAN…»",
 "channels_with_chat": 14,
 "period": "2026-07-01T02:40:38.266837+00:00",
 "conductor_moments": [
  {
   "video_id": "NHt6oqHZYd0",
   "title": "Chau Adorni: TE RECORDAREMOS | TUGO con Nico Guthmann",
   "channel": "GELATINA",
   "kind": "voto",
   "minute": 1,
   "quote": "Eso un poco ordenaba todo, después empezó a desordenarse porque parecía que los bloques que iban a votar esa moción de censura y esa interpe",
   "ratio": 293.33,
   "label": "La sala respondió — chat más activo tras el pedido",
   "pre_rpm": 0.0,
   "post_rpm": 14.67
  },
  {
   "video_id": "l75dqnKslKI",
   "title": "QUÉ OLOR con Charo LÓPEZ, Noe CUSTODIO y Mili GOGGIA 2026-06-30 14:25",
   "channel": "GELATINA",
   "kind": "like",
   "minute": 2,
   "quote": "A mí todo lo que viene en frascos me gusta",
   "ratio": 120.0,
   "label": "La sala respondió — chat más activo tras el pedido",
   "pre_rpm": 0.0,
   "post_rpm": 6.0
  },
  {
   "video_id": "JXVQmuDctII",
   "title": "MIÉRCOLES de PUCHOS HISTÓRICO sobre COMEPECADOS y TALLER de MONSTRUOS y GORE | HAY ALGO AHÍ",
   "channel": "BLENDER",
   "kind": "codigo",
   "minute": 0,
   "quote": "Cargá tu código que sí o sí ganás.",
   "ratio": 80.0,
   "label": "La sala respondió — chat más activo tras el pedido",
   "pre_rpm": 0.0,
   "post_rpm": 4.0
  },
  {
   "video_id": "zwp0lZ6EONI",
   "title": "EL AMIGO DE TU NOVIA VE PAREN LA MANO...| #ESTONOSUCEDIÓ COMPLETO - 30/06 | VORTERIX",
   "channel": "Vorterix",
   "kind": "like",
   "minute": 40,
   "quote": "No me gusta",
   "ratio": 66.67,
   "label": "La sala respondió — chat más activo tras el pedido",
   "pre_rpm": 0.0,
   "post_rpm": 3.33
  },
  {
   "video_id": "U8f_2vIvO7Y",
   "title": "EN VIVO | PUNTO CARAMELO con Julieta Pink, Sol Rosales y Juli Schulkin",
   "channel": "Urbana Play 104.3 FM",
   "kind": "like",
   "minute": 28,
   "quote": "Me gusta eso, eh",
   "ratio": 53.33,
   "label": "La sala respondió — chat más activo tras el pedido",
   "pre_rpm": 0.0,
   "post_rpm": 2.67
  },
  {
   "video_id": "95yJuQx7ol8",
   "title": "“Todo lo que es extraordinario, LIONEL lo hace ordinario” | #GolGana 22/6",
   "channel": "OLGA",
   "kind": "like",
   "minute": 71,
   "quote": "López. Yo estoy un Flaco López. A mí me gusta",
   "ratio": 33.33,
   "label": "La sala respondió — chat más activo tras el pedido",
   "pre_rpm": 0.0,
   "post_rpm": 1.67
  },
  {
   "video_id": "U8f_2vIvO7Y",
   "title": "EN VIVO | PUNTO CARAMELO con Julieta Pink, Sol Rosales y Juli Schulkin",
   "channel": "Urbana Play 104.3 FM",
   "kind": "like",
   "minute": 36,
   "quote": "Me encanta, es lindo, me gusta verlo",
   "ratio": 26.67,
   "label": "La sala respondió — chat más activo tras el pedido",
   "pre_rpm": 0.0,
   "post_rpm": 1.33
  },
  {
   "video_id": "NZnTfvrPb0E",
   "title": "🟠 ¿CÓMO QUEDARON LOS CRUCES DEL  MUNDIAL 2026? l HOY COMO SIEMPRE",
   "channel": " A U R A ",
   "kind": "like",
   "minute": 59,
   "quote": "Sí, me gusta, es muy internacional",
   "ratio": 26.67,
   "label": "La sala respondió — chat más activo tras el pedido",
   "pre_rpm": 0.0,
   "post_rpm": 1.33
  },
  {
   "video_id": "JqkhC1EnyTQ",
   "title": "MESSI pasó más cumpleaños con la selección que con ANTONELA | #GolGana 24/6",
   "channel": "OLGA",
   "kind": "codigo",
   "minute": 40,
   "quote": "Y atentos a este dato también, con el código NATIJ guiondelmedioMBA",
   "ratio": 20.0,
   "label": "La sala respondió — chat más activo tras el pedido",
   "pre_rpm": 0.0,
   "post_rpm": 1.0
  },
  {
   "video_id": "zwp0lZ6EONI",
   "title": "EL AMIGO DE TU NOVIA VE PAREN LA MANO...| #ESTONOSUCEDIÓ COMPLETO - 30/06 | VORTERIX",
   "channel": "Vorterix",
   "kind": "like",
   "minute": 62,
   "quote": "No me gusta, nunca está bien hecho.",
   "ratio": 14.0,
   "label": "La sala respondió — chat más activo tras el pedido",
   "pre_rpm": 0.33,
   "post_rpm": 4.67
  },
  {
   "video_id": "Mbk0Mff3g0c",
   "title": "Ramón Agote y Mauro Fiorenzano en Cash is King: Alejo Rodríguez Cacio - 30/06",
   "channel": "Neura Media",
   "kind": "like",
   "minute": 50,
   "quote": "me gusta mucho",
   "ratio": 13.33,
   "label": "La sala respondió — chat más activo tras el pedido",
   "pre_rpm": 0.0,
   "post_rpm": 0.67
  },
  {
   "video_id": "WCdVYizlDYA",
   "title": "⚽️ GOLGANA con AZZ: Flavio Azzaro, Chute D'attellis, Benito, Sangre y Mouche | OLGA EN VIVO 2026-06-29 14:53",
   "channel": "OLGA",
   "kind": "like",
   "minute": 4,
   "quote": "Me gusta mucho Colombia",
   "ratio": 13.33,
   "label": "La sala respondió — chat más activo tras el pedido",
   "pre_rpm": 0.0,
   "post_rpm": 0.67
  },
  {
   "video_id": "AUSgxGQirlM",
   "title": "LA CIENCIA DE LOS CODIGOS QR con EZE MARTÍNEZ l #deacá - 29/06/26",
   "channel": " A U R A ",
   "kind": "codigo",
   "minute": 82,
   "quote": "Bueno, esto es porque el código QR, dentro de sus miles de bits,",
   "ratio": 13.33,
   "label": "La sala respondió — chat más activo tras el pedido",
   "pre_rpm": 0.0,
   "post_rpm": 0.67
  },
  {
   "video_id": "NKhi31a86K8",
   "title": "¿PREOCUPA LA LESIÓN DEL CUTI ROMERO? | #GolGana 23/6",
   "channel": "OLGA",
   "kind": "like",
   "minute": 121,
   "quote": "Me gusta tener el efectivo",
   "ratio": 13.33,
   "label": "La sala respondió — chat más activo tras el pedido",
   "pre_rpm": 0.0,
   "post_rpm": 0.67
  },
  {
   "video_id": "EwFONN3W5cg",
   "title": "🔴 DOPAMINAS con Guille Bianchi, Agos Palazzolo y Cami Fortunato | VORTERIX EN VIVO",
   "channel": "Vorterix",
   "kind": "like",
   "minute": 69,
   "quote": "Entonces me da un toque, porque me gusta el olor.",
   "ratio": 13.33,
   "label": "La sala respondió — chat más activo tras el pedido",
   "pre_rpm": 0.0,
   "post_rpm": 0.67
  }
 ]
}